readfish/__about__.py
readfish/__init__.py
readfish/__main__.py
readfish/_channels.py
readfish/_cli_args.py
readfish/_cli_base.py
readfish/_compatibility.py
readfish/_config.py
readfish/_loggers.py
readfish/_read_until_client.py
readfish/_statistics.py
readfish/_utils.py
readfish/entry_points/__init__.py
readfish/entry_points/demultiplex.py
readfish/entry_points/stats.py
readfish/entry_points/targets.py
readfish/entry_points/unblock_all.py
readfish/entry_points/validate.py
readfish/plugins/__init__.py
readfish/plugins/_filter.py
readfish/plugins/_mappy.py
readfish/plugins/_no_op.py
readfish/plugins/abc.py
readfish/plugins/deepnano_blitz.py
readfish/plugins/dorado.py
readfish/plugins/mappy.py
readfish/plugins/mappy_rs.py
readfish/plugins/utils.py
readfish/read_until/LICENSE.md
readfish/read_until/__init__.py
readfish/read_until/_version.py
readfish/read_until/base.py
readfish/read_until/read_cache.py
readfish-2024.3.0.dist-info/METADATA
readfish-2024.3.0.dist-info/WHEEL
readfish-2024.3.0.dist-info/entry_points.txt
readfish-2024.3.0.dist-info/licenses/LICENSE
readfish-2024.3.0.dist-info/RECORD
