Metadata-Version: 2.3
Name: readfish
Version: 2024.3.0
Summary: ONT adaptive sampling
Project-URL: Documentation, https://looselab.github.io/readfish
Project-URL: Bug Tracker, https://github.com/LooseLab/readfish/issues
Project-URL: Source Code, https://github.com/LooseLab/readfish
Author: Alexander Payne
Author-email: Rory Munro <rory.munro@nottingham.ac.uk>, Matt Loose <matt.loose@nottingham.ac.uk>
License-Expression: MIT
License-File: LICENSE
Classifier: Development Status :: 4 - Beta
Classifier: Intended Audience :: Science/Research
Classifier: License :: OSI Approved :: MIT License
Classifier: Natural Language :: English
Classifier: Operating System :: OS Independent
Classifier: Programming Language :: Python
Classifier: Programming Language :: Python :: 3
Classifier: Programming Language :: Python :: 3.8
Classifier: Programming Language :: Python :: 3.9
Classifier: Programming Language :: Python :: 3.10
Classifier: Programming Language :: Python :: 3.11
Classifier: Programming Language :: Python :: Implementation :: CPython
Classifier: Topic :: Scientific/Engineering :: Bio-Informatics
Requires-Python: >=3.8
Requires-Dist: cattrs
Requires-Dist: exceptiongroup; python_version < '3.11'
Requires-Dist: minknow-api
Requires-Dist: more-itertools
Requires-Dist: numpy
Requires-Dist: readfish-summarise>=0.2.7
Requires-Dist: readfish[all]
Requires-Dist: rtoml
Provides-Extra: all
Requires-Dist: mappy; extra == 'all'
Requires-Dist: mappy-rs>=0.0.6; extra == 'all'
Requires-Dist: ont-pybasecall-client-lib>=7.4.12; extra == 'all'
Provides-Extra: dev
Requires-Dist: coverage[toml]; extra == 'dev'
Requires-Dist: faqtory; extra == 'dev'
Requires-Dist: furo; extra == 'dev'
Requires-Dist: mappy; extra == 'dev'
Requires-Dist: mappy-rs>=0.0.6; extra == 'dev'
Requires-Dist: myst-parser; extra == 'dev'
Requires-Dist: ont-pybasecall-client-lib>=7.4.12; extra == 'dev'
Requires-Dist: pre-commit; extra == 'dev'
Requires-Dist: pytest; extra == 'dev'
Requires-Dist: sphinx-copybutton; extra == 'dev'
Provides-Extra: docs
Requires-Dist: faqtory; extra == 'docs'
Requires-Dist: furo; extra == 'docs'
Requires-Dist: myst-parser; extra == 'docs'
Requires-Dist: sphinx-copybutton; extra == 'docs'
Provides-Extra: dorado
Requires-Dist: ont-pybasecall-client-lib>=7.4.12; extra == 'dorado'
Provides-Extra: mappy
Requires-Dist: mappy; extra == 'mappy'
Provides-Extra: mappy-rs
Requires-Dist: mappy-rs>=0.0.6; extra == 'mappy-rs'
Provides-Extra: tests
Requires-Dist: coverage[toml]; extra == 'tests'
Requires-Dist: pytest; extra == 'tests'
Provides-Extra: tests-mappy
Requires-Dist: coverage[toml]; extra == 'tests-mappy'
Requires-Dist: mappy; extra == 'tests-mappy'
Requires-Dist: ont-pybasecall-client-lib>=7.4.12; extra == 'tests-mappy'
Requires-Dist: pytest; extra == 'tests-mappy'
